robo_infra/__init__.py
robo_infra/actuators/__init__.py
robo_infra/actuators/brushless.py
robo_infra/actuators/dc_motor.py
robo_infra/actuators/linear.py
robo_infra/actuators/servo.py
robo_infra/actuators/solenoid.py
robo_infra/actuators/stepper.py
robo_infra/cli.py
robo_infra/controllers/__init__.py
robo_infra/controllers/conveyor.py
robo_infra/controllers/differential.py
robo_infra/controllers/gripper.py
robo_infra/controllers/hexapod.py
robo_infra/controllers/joint_group.py
robo_infra/controllers/leg.py
robo_infra/controllers/lock.py
robo_infra/controllers/mavlink.py
robo_infra/controllers/pan_tilt.py
robo_infra/controllers/quadcopter.py
robo_infra/controllers/turntable.py
robo_infra/core/__init__.py
robo_infra/core/actuator.py
robo_infra/core/bus.py
robo_infra/core/can_bus.py
robo_infra/core/controller.py
robo_infra/core/driver.py
robo_infra/core/exceptions.py
robo_infra/core/pin.py
robo_infra/core/sensor.py
robo_infra/core/types.py
robo_infra/drivers/__init__.py
robo_infra/drivers/arduino.py
robo_infra/drivers/bmi270.py
robo_infra/drivers/bno055.py
robo_infra/drivers/dynamixel.py
robo_infra/drivers/gpio.py
robo_infra/drivers/icm20948.py
robo_infra/drivers/l298n.py
robo_infra/drivers/lsm6ds3.py
robo_infra/drivers/odrive.py
robo_infra/drivers/pca9685.py
robo_infra/drivers/simulation.py
robo_infra/drivers/step_dir.py
robo_infra/drivers/tb6612.py
robo_infra/drivers/tmc2209.py
robo_infra/drivers/vesc.py
robo_infra/integrations/__init__.py
robo_infra/integrations/ai_infra.py
robo_infra/integrations/observability.py
robo_infra/integrations/ros2.py
robo_infra/integrations/svc_infra.py
robo_infra/motion/__init__.py
robo_infra/motion/delta.py
robo_infra/motion/dh_parameters.py
robo_infra/motion/fusion.py
robo_infra/motion/ik_solvers.py
robo_infra/motion/kinematics.py
robo_infra/motion/path_planning.py
robo_infra/motion/pid.py
robo_infra/motion/scara.py
robo_infra/motion/stewart.py
robo_infra/motion/trajectory.py
robo_infra/motion/transforms.py
robo_infra-0.5.1.dist-info/LICENSE
robo_infra-0.5.1.dist-info/METADATA
robo_infra-0.5.1.dist-info/WHEEL
robo_infra-0.5.1.dist-info/entry_points.txt
robo_infra-0.5.1.dist-info/RECORD
