Metadata-Version: 2.3
Name: robo-infra
Version: 0.5.1
Summary: Robotics SDK for prototyping and development (Beta)
License: MIT
Keywords: robotics,servo,motor,sensor,raspberry-pi,automation,iot
Author: nfraxlab
Author-email: dev@nfrax.io
Requires-Python: >=3.11,<4.0
Classifier: Development Status :: 4 - Beta
Classifier: Intended Audience :: Developers
Classifier: Intended Audience :: Education
Classifier: Intended Audience :: Science/Research
Classifier: License :: OSI Approved :: MIT License
Classifier: Operating System :: OS Independent
Classifier: Programming Language :: Python :: 3
Classifier: Programming Language :: Python :: 3.11
Classifier: Programming Language :: Python :: 3.12
Classifier: Programming Language :: Python :: 3.13
Classifier: Topic :: Scientific/Engineering
Classifier: Topic :: Software Development :: Libraries :: Python Modules
Classifier: Topic :: System :: Hardware
Classifier: Typing :: Typed
Provides-Extra: ai
Provides-Extra: api
Provides-Extra: cameras
Provides-Extra: can
Provides-Extra: full
Provides-Extra: gpio
Provides-Extra: hardware
Provides-Extra: i2c
Provides-Extra: jetson
Provides-Extra: oak
Provides-Extra: picamera
Provides-Extra: raspberry-pi
Provides-Extra: realsense
Provides-Extra: serial
Provides-Extra: spi
Provides-Extra: vision
Requires-Dist: ai-infra (>=0.1.166,<0.2.0) ; extra == "ai" or extra == "full"
Requires-Dist: depthai (>=2.20) ; extra == "oak" or extra == "cameras"
Requires-Dist: gpiozero (>=2.0) ; (sys_platform == "linux") and (extra == "gpio" or extra == "raspberry-pi" or extra == "hardware" or extra == "full")
Requires-Dist: lgpio (>=0.2) ; (sys_platform == "linux") and (extra == "gpio" or extra == "raspberry-pi" or extra == "hardware" or extra == "full")
Requires-Dist: numpy (>=1.24)
Requires-Dist: opencv-python-headless (>=4.8) ; extra == "vision" or extra == "cameras" or extra == "full"
Requires-Dist: picamera2 (>=0.3) ; (sys_platform == "linux") and (extra == "picamera" or extra == "raspberry-pi")
Requires-Dist: pydantic (>=2.0)
Requires-Dist: pyrealsense2 (>=2.50) ; extra == "realsense" or extra == "cameras"
Requires-Dist: pyserial (>=3.5) ; extra == "serial" or extra == "raspberry-pi" or extra == "jetson" or extra == "hardware" or extra == "full"
Requires-Dist: python-can (>=4.0) ; extra == "can" or extra == "hardware" or extra == "full"
Requires-Dist: smbus2 (>=0.4) ; extra == "i2c" or extra == "raspberry-pi" or extra == "jetson" or extra == "hardware" or extra == "full"
Requires-Dist: spidev (>=3.6) ; (sys_platform == "linux") and (extra == "spi" or extra == "raspberry-pi" or extra == "jetson" or extra == "hardware" or extra == "full")
Requires-Dist: svc-infra (>=0.1.716,<0.2.0) ; extra == "api" or extra == "full"
Requires-Dist: typing-extensions (>=4.0)
Project-URL: Documentation, https://github.com/nfraxlab/robo-infra#readme
Project-URL: Homepage, https://github.com/nfraxlab/robo-infra
Project-URL: Repository, https://github.com/nfraxlab/robo-infra
